mcp_server_esignatures/__init__.py
mcp_server_esignatures/input_schema_contracts.py
mcp_server_esignatures/input_schema_document_elements.py
mcp_server_esignatures/input_schema_templates.py
mcp_server_esignatures/server.py
mcp_server_esignatures-0.1.0.dist-info/METADATA
mcp_server_esignatures-0.1.0.dist-info/WHEEL
mcp_server_esignatures-0.1.0.dist-info/entry_points.txt
mcp_server_esignatures-0.1.0.dist-info/RECORD
