Metadata-Version: 2.4
Name: mcp-server-esignatures
Version: 0.1.0
Summary: MCP server for eSignatures (https://esignatures.com)
Project-URL: Homepage, https://github.com/esignaturescom/mcp-server-perplexity
Project-URL: Repository, https://github.com/esignaturescom/mcp-server-perplexity
Author-email: eSignatures <dev@esignatures.com>
Requires-Python: >=3.10
Requires-Dist: mcp>=1.2.0
Requires-Dist: twine>=6.1.0
